taro/__init__.py
taro/exceptions.py
taro/util.py
tests/__init__.py
tests/test_taro.py
taro-0.0.1.dist-info/LICENSE
taro-0.0.1.dist-info/METADATA
taro-0.0.1.dist-info/WHEEL
taro-0.0.1.dist-info/top_level.txt
taro-0.0.1.dist-info/RECORD
