Metadata-Version: 2.1
Name: taro
Version: 0.0.1
Summary: A package for repeatable rectangular data transformations.
Home-page: https://github.com/a-poor/taro
Author: Austin Poor
Author-email: 45295232+a-poor@users.noreply.github.com
License: UNKNOWN
Platform: UNKNOWN
Classifier: Programming Language :: Python :: 3
Classifier: License :: OSI Approved :: MIT License
Classifier: Operating System :: OS Independent
Classifier: Development Status :: 1 - Planning
Requires-Python: >=3.6
